apppy/aws/__init__.py
apppy/aws/env.py
apppy/aws/fs.py
apppy/aws/fs_fixtures.py
apppy/aws/fs_test.py
apppy/aws/fs_unit_test.py
apppy_aws-0.23.2.dist-info/METADATA
apppy_aws-0.23.2.dist-info/WHEEL
apppy_aws-0.23.2.dist-info/RECORD
