Metadata-Version: 2.4
Name: apppy-aws
Version: 0.23.2
Summary: AWS integrations for server development
Project-URL: Homepage, https://github.com/spals/apppy
Author: Tim Kral
License: MIT
Classifier: License :: OSI Approved :: MIT License
Classifier: Programming Language :: Python :: 3
Requires-Python: >=3.11
Requires-Dist: anyio==4.11.0
Requires-Dist: apppy-env>=0.23.2
Requires-Dist: apppy-fs>=0.23.2
Requires-Dist: apppy-generic>=0.23.2
Requires-Dist: apppy-logger>=0.23.2
Requires-Dist: boto3-stubs[s3]==1.40.49
Requires-Dist: boto3-stubs[secretsmanager]==1.40.49
Requires-Dist: boto3==1.40.49
